pyclass_generator/__init__.py
pyclass_generator/cst.py
pyclass_generator/generator.py
pyclass_generator/utils.py
pyclass_generator-0.1.2.dist-info/METADATA
pyclass_generator-0.1.2.dist-info/WHEEL
pyclass_generator-0.1.2.dist-info/top_level.txt
pyclass_generator-0.1.2.dist-info/RECORD
